xc_ip_info
