Metadata-Version: 1.2
Name: xc-ip-info
Version: 0.4
Summary: 根据ip获取地址信息
Home-page: http://git.izuiyou.com/liutianyi/ip_info
Author: liutianyi
Author-email: liutianyi2014@xiaochuankeji.cn
Maintainer: liutianyi
Maintainer-email: liutianyi2014@xiaochuankeji.cn
License: BSD License
Platform: all
Classifier: Development Status :: 4 - Beta
Classifier: Operating System :: OS Independent
Classifier: Intended Audience :: Developers
Classifier: License :: OSI Approved :: BSD License
Classifier: Programming Language :: Python
Classifier: Programming Language :: Python :: Implementation
Classifier: Programming Language :: Python :: 2
Classifier: Programming Language :: Python :: 2.7
Classifier: Programming Language :: Python :: 3
Classifier: Programming Language :: Python :: 3.4
Classifier: Programming Language :: Python :: 3.5
Classifier: Programming Language :: Python :: 3.6
Classifier: Topic :: Software Development :: Libraries
